{
  "gitSyncId": "6989a863233bc531e8c7654a_7582f6b9-b46c-4469-8771-394d8b0de642",
  "id": "ApproverDashboard_ApproveLeave",
  "pluginId": "restapi-plugin",
  "pluginType": "API",
  "unpublishedAction": {
    "actionConfiguration": {
      "autoGeneratedHeaders": [
        {
          "key": "content-type",
          "value": "application/json"
        }
      ],
      "body": "{\n  \"request_id\": {{ this.params.id }},      \n  \"status\": {{ this.params.status }},\n  \"approver\": {{ appsmith.user.email }}\n}",
      "bodyFormData": [],
      "encodeParamsToggle": true,
      "formData": {
        "apiContentType": "application/json"
      },
      "headers": [],
      "httpMethod": "POST",
      "httpVersion": "HTTP11",
      "paginationType": "NONE",
      "path": "/webhook/api/v1/updatestatus",
      "pluginSpecifiedTemplates": [
        {
          "value": true
        }
      ],
      "queryParameters": [],
      "timeoutInMillisecond": 10000
    },
    "confirmBeforeExecute": false,
    "datasource": {
      "datasourceConfiguration": {
        "url": "http://host.docker.internal:5678"
      },
      "isAutoGenerated": false,
      "name": "DEFAULT_REST_DATASOURCE",
      "pluginId": "restapi-plugin"
    },
    "dynamicBindingPathList": [
      {
        "key": "body"
      }
    ],
    "name": "ApproveLeave",
    "pageId": "ApproverDashboard",
    "runBehaviour": "MANUAL",
    "userSetOnLoad": false
  }
}